wirtual/plugins/cartesia/__init__.py
wirtual/plugins/cartesia/log.py
wirtual/plugins/cartesia/models.py
wirtual/plugins/cartesia/py.typed
wirtual/plugins/cartesia/tts.py
wirtual/plugins/cartesia/version.py
wirtual_plugins_cartesia-0.0.2.dist-info/METADATA
wirtual_plugins_cartesia-0.0.2.dist-info/WHEEL
wirtual_plugins_cartesia-0.0.2.dist-info/top_level.txt
wirtual_plugins_cartesia-0.0.2.dist-info/RECORD
